{
    "alias": "platform.phar",
    "chmod": "0755",
    "directories": [
        "resources",
        "src",
        "vendor/cocur",
        "vendor/commerceguys",
        "vendor/composer",
        "vendor/doctrine",
        "vendor/guzzlehttp",
        "vendor/justinrainbow",
        "vendor/herrera-io",
        "vendor/platformsh",
        "vendor/react",
        "vendor/seld",
        "vendor/stecman",
        "vendor/symfony"
    ],
    "files": [
        "platform",
        "vendor/autoload.php"
    ],
    "git-version": "package_version",
    "main": "platform",
    "output": "platform.phar",
    "stub": true
}
